{"v":"5.12.1","fr":60,"ip":0,"op":90,"w":430,"h":430,"nm":"wired-outline-2563-logo-wechat","ddd":0,"assets":[{"id":"comp_1","nm":"hover-pinch","fr":60,"layers":[{"ddd":0,"ind":1,"ty":4,"nm":"eye-small","parent":2,"sr":1,"ks":{"o":{"a":0,"k":100,"ix":11},"r":{"a":0,"k":0,"ix":10},"p":{"a":0,"k":[3.52,-42,0],"ix":2,"l":2},"a":{"a":0,"k":[1.594,-47.452,0],"ix":1,"l":2},"s":{"a":0,"k":[100,100,100],"ix":6,"l":2}},"ao":0,"shapes":[{"ty":"gr","it":[{"ind":0,"ty":"sh","ix":1,"ks":{"a":1,"k":[{"t":36,"s":[{"i":[[0,0],[0,0]],"o":[[0,0],[0,0]],"v":[[38.344,-47.452],[38.344,-47.452]],"c":false}],"h":1},{"t":39,"s":[{"i":[[0,0],[0,0]],"o":[[0,0],[0,0]],"v":[[58.344,-47.452],[18.344,-47.452]],"c":false}],"h":1},{"i":{"x":0.833,"y":0.833},"o":{"x":0.167,"y":0.167},"t":43,"s":[{"i":[[0,0],[0,0]],"o":[[0,0],[0,0]],"v":[[58.344,-47.452],[18.344,-47.452]],"c":false}]},{"t":47,"s":[{"i":[[0,0],[0,0]],"o":[[0,0],[0,0]],"v":[[38.344,-47.452],[38.344,-47.452]],"c":false}]}],"ix":2},"nm":"Path 2","mn":"ADBE Vector Shape - Group","hd":false},{"ind":1,"ty":"sh","ix":2,"ks":{"a":1,"k":[{"t":36,"s":[{"i":[[0,0],[0,0]],"o":[[0,0],[0,0]],"v":[[-45.656,-47.452],[-45.656,-47.452]],"c":false}],"h":1},{"t":39,"s":[{"i":[[0,0],[0,0]],"o":[[0,0],[0,0]],"v":[[-25.656,-47.452],[-65.656,-47.452]],"c":false}],"h":1},{"i":{"x":0.833,"y":0.833},"o":{"x":0.167,"y":0.167},"t":43,"s":[{"i":[[0,0],[0,0]],"o":[[0,0],[0,0]],"v":[[-25.656,-47.452],[-65.656,-47.452]],"c":false}]},{"t":47,"s":[{"i":[[0,0],[0,0]],"o":[[0,0],[0,0]],"v":[[-45.656,-47.452],[-45.656,-47.452]],"c":false}]}],"ix":2},"nm":"Path 3","mn":"ADBE Vector Shape - Group","hd":false},{"ty":"st","c":{"a":0,"k":[0.031,0.659,0.541,1],"ix":3,"x":"var $bm_rt;\n$bm_rt = comp('wired-outline-2563-logo-wechat').layer('control').effect('secondary')('Color');"},"o":{"a":0,"k":100,"ix":4},"w":{"a":1,"k":[{"t":36,"s":[32],"h":1},{"t":39,"s":[12],"h":1},{"i":{"x":[0.833],"y":[0.833]},"o":{"x":[0.167],"y":[0.167]},"t":43,"s":[12]},{"t":47,"s":[32]}],"ix":5,"x":"var $bm_rt;\n$bm_rt = $bm_mul($bm_div(value, 2), comp('wired-outline-2563-logo-wechat').layer('control').effect('stroke')('Menu'));"},"lc":2,"lj":2,"bm":0,"nm":".secondary","mn":"ADBE Vector Graphic - Stroke","hd":false,"cl":"secondary"},{"ty":"tr","p":{"a":0,"k":[0,0],"ix":2},"a":{"a":0,"k":[0,0],"ix":1},"s":{"a":0,"k":[100,100],"ix":3},"r":{"a":0,"k":0,"ix":6},"o":{"a":0,"k":100,"ix":7},"sk":{"a":0,"k":0,"ix":4},"sa":{"a":0,"k":0,"ix":5},"nm":"Transform"}],"nm":"bubble L","np":3,"cix":2,"bm":0,"ix":1,"mn":"ADBE Vector Group","hd":false}],"ip":0,"op":1800,"st":0,"ct":1,"bm":0},{"ddd":0,"ind":2,"ty":4,"nm":"bubble R","sr":1,"ks":{"o":{"a":0,"k":100,"ix":11},"r":{"a":1,"k":[{"i":{"x":[0.332],"y":[1]},"o":{"x":[0.333],"y":[0]},"t":30,"s":[0]},{"i":{"x":[0.538],"y":[1]},"o":{"x":[0.333],"y":[0]},"t":43,"s":[-10]},{"i":{"x":[0.667],"y":[1]},"o":{"x":[0.333],"y":[0]},"t":58,"s":[6]},{"i":{"x":[0.515],"y":[1]},"o":{"x":[0.333],"y":[0]},"t":76,"s":[-3]},{"t":90,"s":[0]}],"ix":10},"p":{"a":1,"k":[{"i":{"x":0.332,"y":1},"o":{"x":0.333,"y":0},"t":30,"s":[371.48,381.5,0],"to":[0,0,0],"ti":[0,0,0]},{"i":{"x":0.538,"y":1},"o":{"x":0.333,"y":0},"t":36,"s":[371.48,391.5,0],"to":[0,0,0],"ti":[0,0,0]},{"i":{"x":0.667,"y":1},"o":{"x":0.333,"y":0},"t":51,"s":[371.48,376.5,0],"to":[0,0,0],"ti":[0,0,0]},{"i":{"x":0.515,"y":1},"o":{"x":0.333,"y":0},"t":69,"s":[371.48,383.5,0],"to":[0,0,0],"ti":[0,0,0]},{"t":83,"s":[371.48,381.5,0]}],"ix":2,"l":2},"a":{"a":0,"k":[76,109,0],"ix":1,"l":2},"s":{"a":0,"k":[100,100,100],"ix":6,"l":2}},"ao":0,"shapes":[{"ty":"gr","it":[{"ind":0,"ty":"sh","ix":1,"ks":{"a":0,"k":{"i":[[0,-55.059],[-62.525,0],[-10.767,2.993],[0,0],[0,0],[0,29.228],[62.525,0]],"o":[[0,55.059],[11.89,0],[0,0],[0,0],[22.756,-18.235],[0,-55.059],[-62.525,0]],"v":[[-113.211,-10.307],[0,89.386],[34.119,84.779],[76.693,110],[76.172,63.447],[113.211,-10.307],[0,-110]],"c":true},"ix":2},"nm":"Path 1","mn":"ADBE Vector Shape - Group","hd":false},{"ty":"st","c":{"a":0,"k":[0.031,0.659,0.541,1],"ix":3,"x":"var $bm_rt;\n$bm_rt = comp('wired-outline-2563-logo-wechat').layer('control').effect('secondary')('Color');"},"o":{"a":0,"k":100,"ix":4},"w":{"a":0,"k":12,"ix":5,"x":"var $bm_rt;\n$bm_rt = $bm_mul($bm_div(value, 2), comp('wired-outline-2563-logo-wechat').layer('control').effect('stroke')('Menu'));"},"lc":1,"lj":2,"bm":0,"nm":".secondary","mn":"ADBE Vector Graphic - Stroke","hd":false,"cl":"secondary"},{"ty":"tr","p":{"a":0,"k":[0,0],"ix":2},"a":{"a":0,"k":[0,0],"ix":1},"s":{"a":0,"k":[100,100],"ix":3},"r":{"a":0,"k":0,"ix":6},"o":{"a":0,"k":100,"ix":7},"sk":{"a":0,"k":0,"ix":4},"sa":{"a":0,"k":0,"ix":5},"nm":"Transform"}],"nm":"bubble R","np":2,"cix":2,"bm":0,"ix":1,"mn":"ADBE Vector Group","hd":false}],"ip":0,"op":1800,"st":0,"ct":1,"bm":0},{"ddd":0,"ind":3,"ty":4,"nm":"eye-big","parent":4,"sr":1,"ks":{"o":{"a":0,"k":100,"ix":11},"r":{"a":0,"k":0,"ix":10},"p":{"a":0,"k":[1.594,-47.452,0],"ix":2,"l":2},"a":{"a":0,"k":[1.594,-47.452,0],"ix":1,"l":2},"s":{"a":0,"k":[100,100,100],"ix":6,"l":2}},"ao":0,"shapes":[{"ty":"gr","it":[{"ind":0,"ty":"sh","ix":1,"ks":{"a":1,"k":[{"t":6,"s":[{"i":[[0,0],[0,0]],"o":[[0,0],[0,0]],"v":[[48.844,-47.452],[48.844,-47.452]],"c":false}],"h":1},{"t":9,"s":[{"i":[[0,0],[0,0]],"o":[[0,0],[0,0]],"v":[[60.786,-47.174],[28.844,-47.452]],"c":false}],"h":1},{"i":{"x":0.833,"y":0.833},"o":{"x":0.167,"y":0.167},"t":13,"s":[{"i":[[0,0],[0,0]],"o":[[0,0],[0,0]],"v":[[68.844,-47.452],[28.844,-47.452]],"c":false}]},{"t":17,"s":[{"i":[[0,0],[0,0]],"o":[[0,0],[0,0]],"v":[[48.844,-47.452],[48.844,-47.452]],"c":false}],"h":1}],"ix":2},"nm":"Path 2","mn":"ADBE Vector Shape - Group","hd":false},{"ind":1,"ty":"sh","ix":2,"ks":{"a":1,"k":[{"t":6,"s":[{"i":[[0,0],[0,0]],"o":[[0,0],[0,0]],"v":[[-45.656,-47.452],[-45.656,-47.452]],"c":false}],"h":1},{"t":9,"s":[{"i":[[0,0],[0,0]],"o":[[0,0],[0,0]],"v":[[-65.656,-47.452],[-25.656,-47.452]],"c":false}],"h":1},{"i":{"x":0.833,"y":0.833},"o":{"x":0.167,"y":0.167},"t":13,"s":[{"i":[[0,0],[0,0]],"o":[[0,0],[0,0]],"v":[[-65.656,-47.452],[-25.656,-47.452]],"c":false}]},{"t":17,"s":[{"i":[[0,0],[0,0]],"o":[[0,0],[0,0]],"v":[[-45.656,-47.452],[-45.656,-47.452]],"c":false}],"h":1}],"ix":2},"nm":"Path 3","mn":"ADBE Vector Shape - Group","hd":false},{"ty":"st","c":{"a":0,"k":[0.071,0.075,0.192,1],"ix":3,"x":"var $bm_rt;\n$bm_rt = comp('wired-outline-2563-logo-wechat').layer('control').effect('primary')('Color');"},"o":{"a":0,"k":100,"ix":4},"w":{"a":1,"k":[{"t":6,"s":[32],"h":1},{"t":9,"s":[12],"h":1},{"i":{"x":[0.833],"y":[0.833]},"o":{"x":[0.167],"y":[0.167]},"t":13,"s":[12]},{"t":17,"s":[32],"h":1}],"ix":5,"x":"var $bm_rt;\n$bm_rt = $bm_mul($bm_div(value, 2), comp('wired-outline-2563-logo-wechat').layer('control').effect('stroke')('Menu'));"},"lc":2,"lj":2,"bm":0,"nm":".primary","mn":"ADBE Vector Graphic - Stroke","hd":false,"cl":"primary"},{"ty":"tr","p":{"a":0,"k":[0,0],"ix":2},"a":{"a":0,"k":[0,0],"ix":1},"s":{"a":0,"k":[100,100],"ix":3},"r":{"a":0,"k":0,"ix":6},"o":{"a":0,"k":100,"ix":7},"sk":{"a":0,"k":0,"ix":4},"sa":{"a":0,"k":0,"ix":5},"nm":"Transform"}],"nm":"bubble L","np":3,"cix":2,"bm":0,"ix":1,"mn":"ADBE Vector Group","hd":false}],"ip":0,"op":1800,"st":0,"ct":1,"bm":0},{"ddd":0,"ind":4,"ty":4,"nm":"bubble L","sr":1,"ks":{"o":{"a":0,"k":100,"ix":11},"r":{"a":1,"k":[{"i":{"x":[0.332],"y":[1]},"o":{"x":[0.333],"y":[0]},"t":0,"s":[0]},{"i":{"x":[0.538],"y":[1]},"o":{"x":[0.333],"y":[0]},"t":13,"s":[10]},{"i":{"x":[0.667],"y":[1]},"o":{"x":[0.333],"y":[0]},"t":28,"s":[-6]},{"i":{"x":[0.515],"y":[1]},"o":{"x":[0.333],"y":[0]},"t":46,"s":[3]},{"t":60,"s":[0]}],"ix":10},"p":{"a":1,"k":[{"i":{"x":0.332,"y":1},"o":{"x":0.333,"y":0},"t":0,"s":[69.906,313.452,0],"to":[0,0,0],"ti":[0,0,0]},{"i":{"x":0.538,"y":1},"o":{"x":0.333,"y":0},"t":6,"s":[69.906,323.452,0],"to":[0,0,0],"ti":[0,0,0]},{"i":{"x":0.667,"y":1},"o":{"x":0.333,"y":0},"t":21,"s":[69.906,308.452,0],"to":[0,0,0],"ti":[0,0,0]},{"i":{"x":0.515,"y":1},"o":{"x":0.333,"y":0},"t":39,"s":[69.906,315.452,0],"to":[0,0,0],"ti":[0,0,0]},{"t":53,"s":[69.906,313.452,0]}],"ix":2,"l":2},"a":{"a":0,"k":[-91,130,0],"ix":1,"l":2},"s":{"a":0,"k":[100,100,100],"ix":6,"l":2}},"ao":0,"shapes":[{"ty":"gr","it":[{"ind":0,"ty":"sh","ix":1,"ks":{"a":0,"k":{"i":[[71.118,0],[0,-65.546],[-27.09,-21.708],[0,0],[0,0],[-14.155,0],[5.046,61.519]],"o":[[-74.434,0],[0,34.795],[0,0],[0,0],[12.817,3.563],[108.416,0],[-5.003,-61]],"v":[[0.178,-130.952],[-134.597,-12.27],[-90.503,75.531],[-91.124,130.952],[-40.439,100.927],[0.178,106.411],[134.597,-20.952]],"c":true},"ix":2},"nm":"Path 1","mn":"ADBE Vector Shape - Group","hd":false},{"ty":"st","c":{"a":0,"k":[0.071,0.075,0.192,1],"ix":3,"x":"var $bm_rt;\n$bm_rt = comp('wired-outline-2563-logo-wechat').layer('control').effect('primary')('Color');"},"o":{"a":0,"k":100,"ix":4},"w":{"a":0,"k":12,"ix":5,"x":"var $bm_rt;\n$bm_rt = $bm_mul($bm_div(value, 2), comp('wired-outline-2563-logo-wechat').layer('control').effect('stroke')('Menu'));"},"lc":2,"lj":2,"bm":0,"nm":".primary","mn":"ADBE Vector Graphic - Stroke","hd":false,"cl":"primary"},{"ty":"tr","p":{"a":0,"k":[0,0],"ix":2},"a":{"a":0,"k":[0,0],"ix":1},"s":{"a":0,"k":[100,100],"ix":3},"r":{"a":0,"k":0,"ix":6},"o":{"a":0,"k":100,"ix":7},"sk":{"a":0,"k":0,"ix":4},"sa":{"a":0,"k":0,"ix":5},"nm":"Transform"}],"nm":"bubble L","np":2,"cix":2,"bm":0,"ix":1,"mn":"ADBE Vector Group","hd":false},{"ty":"tm","s":{"a":1,"k":[{"i":{"x":[0.833],"y":[0.833]},"o":{"x":[0.167],"y":[0.167]},"t":0,"s":[12.2]},{"i":{"x":[0.833],"y":[0.833]},"o":{"x":[0.167],"y":[0.167]},"t":6,"s":[16.95]},{"i":{"x":[0.833],"y":[0.833]},"o":{"x":[0.167],"y":[0.167]},"t":8,"s":[17.2]},{"i":{"x":[0.833],"y":[0.833]},"o":{"x":[0.167],"y":[0.167]},"t":10,"s":[18.2]},{"i":{"x":[0.833],"y":[0.833]},"o":{"x":[0.167],"y":[0.167]},"t":15,"s":[16.7]},{"i":{"x":[0.833],"y":[0.833]},"o":{"x":[0.167],"y":[0.167]},"t":18,"s":[14.2]},{"i":{"x":[0.833],"y":[0.833]},"o":{"x":[0.167],"y":[0.167]},"t":22,"s":[11.2]},{"i":{"x":[0.833],"y":[0.833]},"o":{"x":[0.167],"y":[0.167]},"t":28,"s":[9.2]},{"i":{"x":[0.833],"y":[0.833]},"o":{"x":[0.167],"y":[0.167]},"t":31,"s":[10.2]},{"i":{"x":[0.833],"y":[0.833]},"o":{"x":[0.167],"y":[0.167]},"t":34,"s":[9.2]},{"i":{"x":[0.833],"y":[0.833]},"o":{"x":[0.167],"y":[0.167]},"t":37,"s":[9.2]},{"i":{"x":[0.833],"y":[0.833]},"o":{"x":[0.167],"y":[0.167]},"t":47,"s":[13.533]},{"i":{"x":[0.833],"y":[0.833]},"o":{"x":[0.167],"y":[0.167]},"t":52,"s":[14.2]},{"i":{"x":[0.833],"y":[0.833]},"o":{"x":[0.167],"y":[0.167]},"t":69,"s":[12.2]},{"t":90,"s":[12.2]}],"ix":1},"e":{"a":1,"k":[{"i":{"x":[0.833],"y":[0.833]},"o":{"x":[0.167],"y":[0.167]},"t":0,"s":[90]},{"i":{"x":[0.833],"y":[0.833]},"o":{"x":[0.167],"y":[0.167]},"t":8,"s":[91]},{"i":{"x":[0.599],"y":[1.092]},"o":{"x":[0.26],"y":[0]},"t":18,"s":[90]},{"i":{"x":[0.627],"y":[1.969]},"o":{"x":[0.288],"y":[0.153]},"t":23,"s":[89.227]},{"i":{"x":[0.648],"y":[0.977]},"o":{"x":[0.31],"y":[0.176]},"t":31,"s":[89.76]},{"i":{"x":[0.833],"y":[0.833]},"o":{"x":[0.327],"y":[-0.026]},"t":41,"s":[86.712]},{"i":{"x":[0.833],"y":[0.833]},"o":{"x":[0.167],"y":[0.167]},"t":49,"s":[88.778]},{"i":{"x":[0.833],"y":[0.833]},"o":{"x":[0.167],"y":[0.167]},"t":51,"s":[90.422]},{"i":{"x":[0.833],"y":[0.833]},"o":{"x":[0.167],"y":[0.167]},"t":59,"s":[92]},{"i":{"x":[0.833],"y":[0.833]},"o":{"x":[0.167],"y":[0.167]},"t":69,"s":[90]},{"i":{"x":[0.833],"y":[0.833]},"o":{"x":[0.167],"y":[0.167]},"t":72,"s":[88.667]},{"i":{"x":[0.667],"y":[1]},"o":{"x":[0.167],"y":[0.167]},"t":78,"s":[89]},{"t":90,"s":[90]}],"ix":2},"o":{"a":0,"k":-123,"ix":3},"m":1,"ix":2,"nm":"Trim Paths 1","mn":"ADBE Vector Filter - Trim","hd":false}],"ip":0,"op":1800,"st":0,"ct":1,"bm":0}]},{"id":"comp_4","nm":"mask","fr":60,"layers":[{"ddd":0,"ind":1,"ty":4,"nm":"bubble R 2","sr":1,"ks":{"o":{"a":0,"k":100,"ix":11},"r":{"a":1,"k":[{"i":{"x":[0.667],"y":[1]},"o":{"x":[0.333],"y":[0]},"t":0,"s":[0]},{"i":{"x":[0.667],"y":[1]},"o":{"x":[0.333],"y":[0]},"t":19,"s":[-10]},{"t":30,"s":[0]}],"ix":10},"p":{"a":1,"k":[{"i":{"x":0.4,"y":1},"o":{"x":0.333,"y":0},"t":0,"s":[371.48,381.5,0],"to":[0,0,0],"ti":[0,0,0]},{"t":30,"s":[310.73,311.5,0]}],"ix":2,"l":2},"a":{"a":0,"k":[76,109,0],"ix":1,"l":2},"s":{"a":1,"k":[{"i":{"x":[0.4,0.4,0.4],"y":[1,1,1]},"o":{"x":[0.333,0.333,0.333],"y":[0,0,0]},"t":0,"s":[100,100,100]},{"t":30,"s":[60,60,100]}],"ix":6,"l":2}},"ao":0,"shapes":[{"ty":"gr","it":[{"ind":0,"ty":"sh","ix":1,"ks":{"a":0,"k":{"i":[[0,-55.059],[-62.525,0],[-10.767,2.993],[0,0],[0,0],[0,29.228],[62.525,0]],"o":[[0,55.059],[11.89,0],[0,0],[0,0],[22.756,-18.235],[0,-55.059],[-62.525,0]],"v":[[-113.211,-10.307],[0,89.386],[34.119,84.779],[76.693,110],[76.172,63.447],[113.211,-10.307],[0,-110]],"c":true},"ix":2},"nm":"Path 1","mn":"ADBE Vector Shape - Group","hd":false},{"ty":"fl","c":{"a":0,"k":[1,0,0,1],"ix":4},"o":{"a":0,"k":100,"ix":5},"r":1,"bm":0,"nm":"Fill 1","mn":"ADBE Vector Graphic - Fill","hd":false},{"ty":"tr","p":{"a":0,"k":[0,0],"ix":2},"a":{"a":0,"k":[0,0],"ix":1},"s":{"a":0,"k":[100,100],"ix":3},"r":{"a":0,"k":0,"ix":6},"o":{"a":0,"k":100,"ix":7},"sk":{"a":0,"k":0,"ix":4},"sa":{"a":0,"k":0,"ix":5},"nm":"Transform"}],"nm":"bubble R","np":2,"cix":2,"bm":0,"ix":1,"mn":"ADBE Vector Group","hd":false}],"ip":0,"op":1800,"st":0,"ct":1,"bm":0},{"ddd":0,"ind":2,"ty":4,"nm":"bubble L 2","sr":1,"ks":{"o":{"a":0,"k":100,"ix":11},"r":{"a":1,"k":[{"i":{"x":[0.667],"y":[1]},"o":{"x":[0.333],"y":[0]},"t":0,"s":[0]},{"i":{"x":[0.667],"y":[1]},"o":{"x":[0.333],"y":[0]},"t":9,"s":[10]},{"t":30,"s":[0]}],"ix":10},"p":{"a":1,"k":[{"i":{"x":0.4,"y":1},"o":{"x":0.333,"y":0},"t":0,"s":[69.906,313.452,0],"to":[0,0,0],"ti":[0,0,0]},{"t":30,"s":[128.406,270.952,0]}],"ix":2,"l":2},"a":{"a":0,"k":[-91,130,0],"ix":1,"l":2},"s":{"a":1,"k":[{"i":{"x":[0.4,0.4,0.4],"y":[1,1,1]},"o":{"x":[0.333,0.333,0.333],"y":[0,0,0]},"t":0,"s":[100,100,100]},{"t":30,"s":[60.7,60.7,100]}],"ix":6,"l":2}},"ao":0,"shapes":[{"ty":"gr","it":[{"ind":0,"ty":"sh","ix":1,"ks":{"a":0,"k":{"i":[[71.118,0],[0,-65.546],[-27.09,-21.708],[0,0],[0,0],[-14.155,0],[5.046,61.519]],"o":[[-74.434,0],[0,34.795],[0,0],[0,0],[12.817,3.563],[108.416,0],[-5.003,-61]],"v":[[0.178,-130.952],[-134.597,-12.27],[-90.503,75.531],[-91.124,130.952],[-40.439,100.927],[0.178,106.411],[134.597,-20.952]],"c":true},"ix":2},"nm":"Path 1","mn":"ADBE Vector Shape - Group","hd":false},{"ty":"fl","c":{"a":0,"k":[1,0,0,1],"ix":4},"o":{"a":0,"k":100,"ix":5},"r":1,"bm":0,"nm":"Fill 1","mn":"ADBE Vector Graphic - Fill","hd":false},{"ty":"tr","p":{"a":0,"k":[0,0],"ix":2},"a":{"a":0,"k":[0,0],"ix":1},"s":{"a":0,"k":[100,100],"ix":3},"r":{"a":0,"k":0,"ix":6},"o":{"a":0,"k":100,"ix":7},"sk":{"a":0,"k":0,"ix":4},"sa":{"a":0,"k":0,"ix":5},"nm":"Transform"}],"nm":"bubble L","np":2,"cix":2,"bm":0,"ix":1,"mn":"ADBE Vector Group","hd":false}],"ip":0,"op":1800,"st":0,"ct":1,"bm":0}]}],"layers":[{"ddd":0,"ind":1,"ty":3,"nm":"control","sr":1,"ks":{"o":{"a":0,"k":0,"ix":11},"r":{"a":0,"k":0,"ix":10},"p":{"a":0,"k":[0,0],"ix":2,"l":2},"a":{"a":0,"k":[0,0,0],"ix":1,"l":2},"s":{"a":0,"k":[100,100,100],"ix":6,"l":2}},"ao":0,"ef":[{"ty":5,"nm":"stroke","np":3,"mn":"Pseudo/@@9gcPzv7ATgal2sC3CDKxmQ","ix":1,"en":1,"ef":[{"ty":7,"nm":"Menu","mn":"Pseudo/@@9gcPzv7ATgal2sC3CDKxmQ-0001","ix":1,"v":{"a":0,"k":2,"ix":1}}]},{"ty":5,"nm":"primary","np":3,"mn":"ADBE Color Control","ix":2,"en":1,"ef":[{"ty":2,"nm":"Color","mn":"ADBE Color Control-0001","ix":1,"v":{"a":0,"k":[0.071,0.075,0.192],"ix":1}}]},{"ty":5,"nm":"secondary","np":3,"mn":"ADBE Color Control","ix":3,"en":1,"ef":[{"ty":2,"nm":"Color","mn":"ADBE Color Control-0001","ix":1,"v":{"a":0,"k":[0.031,0.659,0.541],"ix":1}}]}],"ip":0,"op":241,"st":0,"bm":0},{"ddd":0,"ind":3,"ty":0,"nm":"hover-pinch","refId":"comp_1","sr":1,"ks":{"o":{"a":0,"k":100,"ix":11},"r":{"a":0,"k":0,"ix":10},"p":{"a":0,"k":[215,215,0],"ix":2,"l":2},"a":{"a":0,"k":[215,215,0],"ix":1,"l":2},"s":{"a":0,"k":[100,100,100],"ix":6,"l":2}},"ao":0,"w":430,"h":430,"ip":0,"op":100,"st":0,"bm":0}],"markers":[{"tm":0,"cm":"default:hover-pinch","dr":90}],"props":{}}